rems/Config.py
rems/LiteOperator.py
rems/Operator.py
rems/RayOperator.py
rems/__init__.py
rems/_static_version.py
rems/_version.py
rems/device/BasicDeviceBase.py
rems/device/DeviceBase.py
rems/device/DriveBase.py
rems/device/ObserveStateBase.py
rems/device/SenseBase.py
rems/device/__init__.py
rems/device/imu/ImuDevice.py
rems/device/imu/Imu_interface.py
rems/device/imu/__init__.py
rems/device/webots/WebotsBinder.py
rems/device/webots/WebotsDrive.py
rems/device/webots/WebotsSense.py
rems/device/webots/__init__.py
rems/inputs/FileCsvInput.py
rems/inputs/FileInput.py
rems/inputs/HockInput.py
rems/inputs/InputBase.py
rems/inputs/KeyboardInput.py
rems/inputs/__init__.py
rems/inputs/estop_callback.py
rems/inputs/joy/JOYSTICK_KEYMAP.py
rems/inputs/joy/JoyManipulator.py
rems/inputs/joy/JoystickInput.py
rems/inputs/joy/__init__.py
rems/inputs/key/KEYBOARD_KEYMAP.py
rems/inputs/key/KeyboardInput.py
rems/inputs/key/__init__.py
rems/outputs/AnimationOutput.py
rems/outputs/FileCsvOutput.py
rems/outputs/FileOutput.py
rems/outputs/GraphOutput.py
rems/outputs/OutputBase.py
rems/outputs/PlotlyHelper.py
rems/outputs/RealTimeFigOutputBase.py
rems/outputs/__init__.py
rems/process/ProcessSystem.py
rems/process/TestProcess.py
rems/process/__init__.py
rems/robot_def/Manipulator5DoF.py
rems/robot_def/MecanumDriveType.py
rems/robot_def/WoodbotDef.py
rems/robot_def/__init__.py
rems/robot_def/webots/YoubotArmDef.py
rems/robot_def/webots/YoubotBaseDef.py
rems/robot_def/webots/YoubotDef.py
rems/robot_def/webots/__init__.py
rems/robots/JacobianModel.py
rems/robots/NopRobot.py
rems/robots/RobotBase.py
rems/robots/RobotBaseAsync.py
rems/robots/RobotDefBase.py
rems/robots/RobotThread.py
rems/robots/RunConfig.py
rems/robots/__init__.py
rems/robots/bind_robot.py
rems/sim_handler/LiteOperator.py
rems/sim_handler/ProcessActor.py
rems/sim_handler/RayOperator.py
rems/sim_handler/SimActor.py
rems/sim_handler/SystemDefault.py
rems/sim_handler/__init__.py
rems/sim_handler/job_background/JobHandler.py
rems-0.3.2.dist-info/METADATA
rems-0.3.2.dist-info/WHEEL
rems-0.3.2.dist-info/top_level.txt
rems-0.3.2.dist-info/RECORD
